wdgaf/__init__.py
wdgaf/__main__.py
wdgaf/gaf.py
wdgaf/wdgaf.py
wdgaf/grammar/grammar.lark
wdgaf/modules/__init__.py
wdgaf/modules/fu_config.py
wdgaf/modules/fu_keywords.py
wdgaf/modules/fu_math.py
wdgaf/modules/fu_plot.py
wdgaf/modules/fu_util.py
wdgaf/modules/process_tree.py
WDGAF-1.0.7.dist-info/LICENSE
WDGAF-1.0.7.dist-info/METADATA
WDGAF-1.0.7.dist-info/WHEEL
WDGAF-1.0.7.dist-info/entry_points.txt
WDGAF-1.0.7.dist-info/top_level.txt
WDGAF-1.0.7.dist-info/RECORD
