Metadata-Version: 2.1
Name: WDGAF
Version: 1.0.7
Summary: We Do Give a Figure
Home-page: https://github.com/rajp152k/Compilers-II
Author: WDGAF
Author-email: rajp152k@gmail.com
License: MIT
Platform: UNKNOWN
Classifier: License :: OSI Approved :: MIT License
Classifier: Programming Language :: Python :: 3
Classifier: Programming Language :: Python :: 3.8
Requires-Dist: matplotlib
Requires-Dist: numpy
Requires-Dist: lark-parser
